{
  "cols": [
    {
      "type": "position",
      "label": "CF (min 1 PA)",
      "value": "CF"
    },
    {
      "type": "year",
      "label": "Played in 2021 season",
      "value": 2021
    },
    {
      "type": "team",
      "image": "https://static.wbsc.org/assets/flags/ioc/BEL.svg",
      "label": "Belgium NT",
      "value": "143"
    }
  ],
  "rows": [
    {
      "type": "team",
      "image": "https://static.wbsc.org/upload/20c6919f-5149-b21e-dc0e-34879b702f4f.png",
      "label": "Braine Black Rickers",
      "value": "1553"
    },
    {
      "type": "team",
      "image": "https://static.wbsc.org/upload/1aba8bb9-6d31-0d64-b3ec-fbb43cc12c68.png",
      "label": "Merchtem Cats",
      "value": "1476"
    },
    {
      "type": "tournament",
      "label": "Softball Ladies D1 (BE)",
      "value": "SLD1",
      "federation_id": 143
    }
  ]
}