{
  "cols": [
    {
      "type": "position",
      "label": "1B (min 1 PA)",
      "value": "1B"
    },
    {
      "type": "seasonal_pitching_ip",
      "label": "50 IP+ Season",
      "value": 105
    },
    {
      "type": "tournament",
      "label": "Softball Ladies D1 (BE)",
      "value": "SLD1",
      "federation_id": 143
    }
  ],
  "rows": [
    {
      "type": "team",
      "image": "https://static.wbsc.org/upload/7784025f-15e3-9d72-ec0a-5cea1fb36fac.png",
      "label": "Antwerp Eagles",
      "value": "1474"
    },
    {
      "type": "team",
      "image": "https://static.wbsc.org/upload/dfb15b29-c3d5-e17b-16ce-fea5adbc7c83.png",
      "label": "Stabroek Chicaboo`s",
      "value": "1361"
    },
    {
      "type": "team",
      "image": "https://static.wbsc.org/assets/flags/ioc/BEL.svg",
      "label": "Belgium NT",
      "value": "143"
    }
  ],
  "answers": {
    "0-0": 53,
    "0-1": 11,
    "0-2": 34,
    "1-0": 84,
    "1-1": 14,
    "1-2": 36,
    "2-0": 212,
    "2-1": 55,
    "2-2": 59
  }
}