{
  "cols": [
    {
      "type": "position",
      "label": "3B (min 1 PA)",
      "value": "3B"
    },
    {
      "type": "year",
      "label": "Played in 2025 season",
      "value": 2025
    },
    {
      "type": "team",
      "image": "https://static.wbsc.org/assets/flags/ioc/FRA.svg",
      "label": "France NT",
      "value": "14"
    }
  ],
  "rows": [
    {
      "type": "team",
      "image": "https://static.wbsc.org/upload/db8cb428-f188-8cd5-1354-4006e912897a.jpg",
      "label": "Metz Cometz",
      "value": "1712"
    },
    {
      "type": "team",
      "image": "https://static.wbsc.org/upload/51a28c3c-a894-cc4d-30ca-b8c705e5bd5d.png",
      "label": "3M Barracudas Baseball Université Club",
      "value": "1385"
    },
    {
      "type": "tournament",
      "label": "Championnat de France D1 BB (FR)",
      "value": "FRA-D1BB",
      "federation_id": 14
    }
  ],
  "answers": {
    "0-0": 24,
    "0-1": 38,
    "0-2": 8,
    "1-0": 45,
    "1-1": 74,
    "1-2": 40,
    "2-0": 118,
    "2-1": 219,
    "2-2": 85
  }
}