{
  "cols": [
    {
      "type": "position",
      "label": "CF (min 1 PA)",
      "value": "CF"
    },
    {
      "type": "seasonal_avg",
      "label": ">0.300 avg Season (min. 10 pa)",
      "value": 0.3
    },
    {
      "type": "tournament",
      "label": "Serie A Baseball (IT)",
      "value": "ITA-SERIE-A1-M-BB",
      "federation_id": 2
    }
  ],
  "rows": [
    {
      "type": "team",
      "image": "https://static.wbsc.org/assets/cms/teams/logo/ca46571b-ff40-12b6-b72f-6adf48977f33.jpg",
      "label": "CROCETTA BASEBALL CLUB A.S.D.",
      "value": "374"
    },
    {
      "type": "team",
      "image": "https://static.wbsc.org/assets/cms/teams/logo/09fa8d5d-3beb-0f14-7d8e-8d48078672a2.jpg",
      "label": "A.S.D. SAN MARINO BASEBALL CLUB",
      "value": "331"
    },
    {
      "type": "team",
      "image": "https://static.wbsc.org/assets/flags/ioc/ITA.svg",
      "label": "Italy NT",
      "value": "2"
    }
  ]
}