{
  "cols": [
    {
      "type": "seasonal_pitching_ip",
      "label": "50 IP+ Season",
      "value": 105
    },
    {
      "type": "seasonal_pitching_fip",
      "label": "<2.50 FIP Season (min. 10 ip)",
      "value": 3
    },
    {
      "type": "tournament",
      "label": "Serie A Baseball (IT)",
      "value": "ITA-SERIE-A1-M-BB",
      "federation_id": 2
    }
  ],
  "rows": [
    {
      "type": "team",
      "image": "https://static.wbsc.org/assets/cms/teams/logo/12f8bd4d-1eda-665a-5e81-446fa51508e2.jpg",
      "label": "A.S.D. CODOGNO BAS. `67",
      "value": "359"
    },
    {
      "type": "team",
      "image": "https://static.wbsc.org/upload/867c2c87-a075-4811-3a29-71da8dafa1a7.svg",
      "label": "1949 PARMA BASEBALL CLUB ASD",
      "value": "333"
    },
    {
      "type": "team",
      "image": "https://static.wbsc.org/assets/flags/ioc/ITA.svg",
      "label": "Italy NT",
      "value": "2"
    }
  ]
}